Metadata-Version: 2.1
Name: windshield
Version: 0.0.11
Summary: Predict point in distrct
Home-page: https://github.com/pypa/sampleproject
Author: Yang Xiaoyu
Author-email: yangxiaoyu@flashexpress.com
License: MIT
Platform: UNKNOWN
Classifier: Programming Language :: Python :: 3
Classifier: License :: OSI Approved :: MIT License
Classifier: Operating System :: OS Independent
Requires-Python: >=3.8
